intra/__init__.py
intra/admin.py
intra/apps.py
intra/intra_settings.py
intra/urls.py
tests/__init__.py
tests/settings.py
tests/tests.py
tests/urls.py
django_intra-0.2.2.dist-info/LICENSE
django_intra-0.2.2.dist-info/METADATA
django_intra-0.2.2.dist-info/WHEEL
django_intra-0.2.2.dist-info/top_level.txt
django_intra-0.2.2.dist-info/RECORD
