Metadata-Version: 2.1
Name: django-intra
Version: 0.2.2
Summary: An extension of the Django admin application with special features
Home-page: https://github.com/ahmdhjj/django-intra
Author: ahmdhjj
License: MIT License
Project-URL: Documentation, https://ahmdhjj.github.io/django-intra/
Project-URL: Source, https://github.com/ahmdhjj/django-intra
Project-URL: Tracker, https://github.com/ahmdhjj/django-intra/issues
Classifier: Environment :: Web Environment
Classifier: Framework :: Django
Classifier: Intended Audience :: Developers
Classifier: License :: OSI Approved :: MIT License
Classifier: Operating System :: OS Independent
Classifier: Programming Language :: Python :: 3.8
Classifier: Programming Language :: Python :: 3.9
Classifier: Programming Language :: Python :: 3.10
Classifier: Programming Language :: Python :: 3.11
Classifier: Programming Language :: Python :: 3.12
Requires-Python: >=3.8
License-File: LICENSE
Requires-Dist: Django>=4.2
